{"manuscript_title": "\u7855\u535a\u82f1\u8bed\u8bfe\u7a0b\u5f00\u8bbe\u7684\u5fc5\u8981\u6027\u7814\u7a76", "viscosity": "stringy", "status": "under_review", "created_at": "2026-03-03T08:52:02.812636+00:00", "author_name": "Ovo\u5395\u6240\u76d1\u63a7ovO", "user_id": "12740084-d7fc-4358-8477-642a9679d95c", "institution": "\u7d20\u793e\u91cc\u8eba\u5927\u5b66", "social_media": null, "co_authors": [], "special_issue": null, "screened_at": "2026-03-06T01:15:02.324+00:00", "screened_by": "05614adb-6e9d-40ab-b2cd-921413c80755", "screening_notes": null, "solicited_topic": null, "discipline": "humanities", "promoted_to_septic_at": null, "promoted_to_stone_at": null, "discipline_user_edited": true, "hidden": false, "hidden_by": null, "hidden_at": null, "comment_count": 0, "unique_commenters": 0, "zone": "latrine", "latrine_recency": 1, "latrine_sort_key": "a588d022cb7e19a5d058fee12bc256ec"}