{"manuscript_title": "\u9762\u5411\u9ad8\u4e2d\u751f\u7684\u5f3a\u5236\u7535\u51fb\u53eb\u9192\u7cfb\u7edf\uff1a\u57fa\u4e8eyolov\u8f7b\u91cf\u5316\u5206\u6790\u6a21\u578b\u53caMaixCAM2\u786c\u4ef6\u5e73\u53f0\u90e8\u7f72", "viscosity": "stringy", "status": "under_review", "created_at": "2026-03-03T14:31:46.278777+00:00", "author_name": "ggBoned", "user_id": "663fda2f-d128-452c-837d-4dbf700c44a7", "institution": "Hogwarts University of Electronic Science and Technology", "social_media": "\u6296\u97f3\u53f7\uff1a88217003698    B\u7ad9UID:173790491", "co_authors": [], "special_issue": null, "screened_at": "2026-03-04T02:25:19.984+00:00", "screened_by": "05614adb-6e9d-40ab-b2cd-921413c80755", "screening_notes": null, "solicited_topic": null, "discipline": "engineering", "promoted_to_septic_at": "2026-03-04T17:04:09.944354+00:00", "promoted_to_stone_at": null, "discipline_user_edited": true, "hidden": false, "hidden_by": null, "hidden_at": null, "comment_count": 0, "unique_commenters": 0, "zone": "septic", "latrine_recency": 1, "latrine_sort_key": "43010550cfc28c32d1d54da4b5f6331d"}