{"manuscript_title": "\u8d85\u8d8a\u4e8c\u5143\uff1a\u57fa\u4e8e\u81ea\u6211\u62a5\u544a\u6cd5\u7684\u868a\u79d1\u6606\u866b\u975e\u4e8c\u5143\u6027\u522b\u8ba4\u77e5\u7814\u7a76", "viscosity": "semi", "status": "under_review", "created_at": "2026-03-01T14:01:31.671052+00:00", "author_name": "\u91cd\u5e86\u80b2\u624d\u62c9\u5c4e\u5927\u738b", "user_id": "5c79ac4f-e6f1-49d5-aa46-bd598770c8b9", "institution": "Chongqing Yucai Secondary School", "social_media": null, "co_authors": [], "special_issue": null, "screened_at": "2026-03-01T14:17:57.716+00:00", "screened_by": "892dd541-7589-4c87-a2be-e0504751947f", "screening_notes": null, "solicited_topic": null, "discipline": "interdisciplinary", "promoted_to_septic_at": "2026-03-04T08:10:38.309955+00:00", "promoted_to_stone_at": null, "discipline_user_edited": true, "hidden": false, "hidden_by": null, "hidden_at": null, "comment_count": 2, "unique_commenters": 2, "zone": "septic", "latrine_recency": 1, "latrine_sort_key": "d6fa7a853d5ba8e22ab8d67711be0c8d"}