{"manuscript_title": "\u4e2d\u6587\u4e92\u8054\u7f51\u4f2a\u5b66\u672f\u4e9a\u6587\u5316\u7684\u521b\u4f5c\u6a21\u5f0f\u7814\u7a76 \u2014\u2014 \u4ee5\u300aSHIT\u300b\u671f\u520a\u4e3a\u4e2d\u5fc3", "viscosity": "stringy", "status": "under_review", "created_at": "2026-02-25T17:41:11.838868+00:00", "author_name": "\u6797\u58a8\u7fbd", "user_id": "9c9181f9-3b83-4a34-9f17-f46df1462579", "institution": "\u91cc\u68ee\u5821\u56fd\u7acb\u4eba\u6587\u793e\u4f1a\u79d1\u5b66\u9662", "social_media": "\u54d4\u54e9\u54d4\u54e9@\u9759\u89c2\u661f\u8fdc", "co_authors": [], "special_issue": null, "screened_at": null, "screened_by": null, "screening_notes": null, "solicited_topic": null, "discipline": "law_social", "promoted_to_septic_at": "2026-02-25T17:41:11.838868+00:00", "promoted_to_stone_at": null, "discipline_user_edited": true, "hidden": false, "hidden_by": null, "hidden_at": null, "comment_count": 1, "unique_commenters": 1, "zone": "septic", "latrine_recency": 1, "latrine_sort_key": "ad57c7326148edef8b6bbdec96565d6c"}