{"manuscript_title": "\u5b66\u6821\u5c42\u6b21\u5dee\u5f02\u4e0b\u9ad8\u4e2d\u8868\u767d\u5899\u5185\u5bb9\u751f\u6001\u5bf9\u6bd4\u7814\u7a76", "viscosity": "stringy", "status": "under_review", "created_at": "2026-03-03T16:08:58.733395+00:00", "author_name": "SAwassnn", "user_id": "30e4c1da-7ac7-424f-824c-b7ef1a536a41", "institution": "TCU", "social_media": null, "co_authors": [], "special_issue": null, "screened_at": "2026-03-03T19:18:50.169+00:00", "screened_by": "a9622d6b-b09e-4d74-8775-a7db934b78bc", "screening_notes": null, "solicited_topic": null, "discipline": "law_social", "promoted_to_septic_at": null, "promoted_to_stone_at": null, "discipline_user_edited": true, "hidden": false, "hidden_by": null, "hidden_at": null, "comment_count": 0, "unique_commenters": 0, "zone": "sediment", "latrine_recency": 1, "latrine_sort_key": "fa32dd2876055d4da0e207abc6bc3cf0"}