{"manuscript_title": "\u7406\u60f3\u8f66\u4f4d\u4e3a\u5565\u4e71\u505c\uff1a\u57fa\u4e8ePDCA\u6076\u6027\u5faa\u73af\u7406\u8bba\u63a2\u8ba8\u5982\u4f55\u80fd\u5728\u516c\u5171\u573a\u6240\u8fd9\u4e48\u539a\u8138\u76ae", "viscosity": "stringy", "status": "under_review", "created_at": "2026-03-02T06:17:14.923121+00:00", "author_name": "\u9f99\u50b2\u5929", "user_id": "e50ad94f-b79e-4599-9c16-849c3cc04e27", "institution": "\u503e\u57ce\u6247\u4ef8\u811a\u5b66\u9662", "social_media": "\u771f\u80fd\u53d1\u51fa\u6765\u518dtag\u6296\u97f3\u53f7", "co_authors": [], "special_issue": null, "screened_at": "2026-03-02T06:26:15.089+00:00", "screened_by": "a9622d6b-b09e-4d74-8775-a7db934b78bc", "screening_notes": null, "solicited_topic": null, "discipline": "humanities", "promoted_to_septic_at": null, "promoted_to_stone_at": null, "discipline_user_edited": true, "hidden": false, "hidden_by": null, "hidden_at": null, "comment_count": 8, "unique_commenters": 8, "zone": "sediment", "latrine_recency": 1, "latrine_sort_key": "9a66b74bfedaa877d48eb18eca12ce36"}