{"manuscript_title": "\u9a6f\u9f99\u4e0e\u661f\u8230\uff1a\u201c\u8fc7\u65f6\u201d\u201c\u672a\u5f00\u53d1\u201d\u6280\u80fd\u7684\u5f53\u4ee3\u9002\u914d\u8def\u5f84\u63a2\u6790", "viscosity": "stringy", "status": "under_review", "created_at": "2026-03-03T08:31:04.633752+00:00", "author_name": "e.g.\u7ba1\u996d\u7ba1\u9971", "user_id": "4357a354-bb41-4316-97cc-003b1ecfcb5c", "institution": "e.g.\u4ed6\u4e61\u9047\u6545\u53f2\u5927\u5b66", "social_media": "\u6296\u97f3\uff1a\u7ba1\u996d\u7ba1\u9971", "co_authors": [], "special_issue": null, "screened_at": "2026-03-06T01:27:33.524+00:00", "screened_by": "05614adb-6e9d-40ab-b2cd-921413c80755", "screening_notes": null, "solicited_topic": null, "discipline": "interdisciplinary", "promoted_to_septic_at": null, "promoted_to_stone_at": null, "discipline_user_edited": true, "hidden": false, "hidden_by": null, "hidden_at": null, "comment_count": 0, "unique_commenters": 0, "zone": "latrine", "latrine_recency": 1, "latrine_sort_key": "adc17ba1a27a6da0d3147f86e6cebbff"}