{"manuscript_title": "\u738b\u8005\u8363\u8000\u56db\u7ea7\u53cc\u65b9\u5bf9\u6297\u8def\u4e92\u76f8\u88c5\u50bb\u7684\u7834\u5c40\u70b9", "viscosity": "stringy", "status": "under_review", "created_at": "2026-03-02T05:48:43.703124+00:00", "author_name": "Sakura", "user_id": "fead877d-3b91-4333-b9e0-8762204f3878", "institution": "\u6492\u54c8\u62c9\u5927\u5b66", "social_media": "dy1924899136", "co_authors": [], "special_issue": null, "screened_at": "2026-03-02T06:04:09.022+00:00", "screened_by": "a9622d6b-b09e-4d74-8775-a7db934b78bc", "screening_notes": null, "solicited_topic": null, "discipline": "engineering", "promoted_to_septic_at": "2026-03-02T06:42:00.458013+00:00", "promoted_to_stone_at": "2026-03-05T07:49:22.46318+00:00", "discipline_user_edited": true, "hidden": false, "hidden_by": null, "hidden_at": null, "comment_count": 41, "unique_commenters": 35, "zone": "septic", "latrine_recency": 1, "latrine_sort_key": "d24de99f05c3afa49954eacdfb4f9159"}