{"manuscript_title": "\u732bmeme\u5b66\u5bfc\u8bba  \u2014\u2014\u4e00\u9879\u5173\u4e8e\u4eba\u7c7b\u4e3a\u4f55\u6c89\u8ff7\u4e8e\u8ba9\u732b\u66ff\u81ea\u5df1\u8bf4\u8bdd\u7684\u975e\u4e25\u8083\u7814\u7a76", "viscosity": "stringy", "status": "under_review", "created_at": "2026-02-22T13:00:48.484561+00:00", "author_name": "\u4e00\u4e2a\u79cb\u5343\u98de\u98de\u98de\u4eba", "user_id": "f7e1181f-cc02-44f1-8cbb-4d278e43e91c", "institution": "\u65e0", "social_media": "UID:1285577691\uff08\u54d4\u54e9\u54d4\u54e9\uff09", "co_authors": [], "special_issue": null, "screened_at": null, "screened_by": null, "screening_notes": null, "solicited_topic": null, "discipline": "interdisciplinary", "promoted_to_septic_at": null, "promoted_to_stone_at": null, "discipline_user_edited": false, "hidden": false, "hidden_by": null, "hidden_at": null, "comment_count": 0, "unique_commenters": 0, "zone": "latrine", "latrine_recency": 1, "latrine_sort_key": "872e0ed0f413214a30570057bc7295f2"}